{"status": true, "time": "2020/04/30 12:09", "title": "BEJ48 春风的另一半公演各队鸡腿详细比例", "data": [{"id": "11", "parent": "", "name": "BEJ48", "color": "#eeeeee"}, {"id": "1101", "parent": "11", "name": "Team B", "color": "#ff2471"}, {"id": "1102", "parent": "11", "name": "Team E", "color": "#0cc8c3"}, {"id": "1103", "parent": "11", "name": "Team J", "color": "#006ab7"}, {"id": "1104", "parent": "11", "name": "预备生", "color": "#888888"}, {"id": "7984906292", "parent": "1104", "name": "张睿怡", "value": 21553}, {"id": "7984906291", "parent": "1104", "name": "王丹妮", "value": 450}, {"id": "4998561802", "parent": "1101", "name": "宁轲", "value": 35280}, {"id": "4998561801", "parent": "1101", "name": "吕蕊", "value": 1845}, {"id": "4528799751", "parent": "1102", "name": "张智杰", "value": 14720}, {"id": "711746", "parent": "1103", "name": "周湘", "value": 7140}, {"id": "711739", "parent": "1102", "name": "熊鑫", "value": 4280}, {"id": "711732", "parent": "1102", "name": "彭嘉敏", "value": 25448}, {"id": "679466", "parent": "1102", "name": "王雨兰", "value": 6485}, {"id": "623828", "parent": "1102", "name": "李娜", "value": 113173}, {"id": "618319", "parent": "1101", "name": "程戈", "value": 5230}, {"id": "614528", "parent": "1103", "name": "柏欣妤", "value": 20203}, {"id": "610042", "parent": "1103", "name": "唐霖", "value": 24078}, {"id": "609002", "parent": "1101", "name": "赵天杨", "value": 5010}, {"id": "538697", "parent": "1101", "name": "沈小爱", "value": 9525}, {"id": "528337", "parent": "1103", "name": "刘一菲", "value": 30186}, {"id": "528335", "parent": "1103", "name": "金锣赛", "value": 8530}, {"id": "528329", "parent": "1101", "name": "孙晓艳", "value": 1430}, {"id": "480675", "parent": "1102", "name": "张爱静", "value": 2805}, {"id": "407127", "parent": "1103", "name": "张怀瑾", "value": 36390}, {"id": "407126", "parent": "1103", "name": "杨晔", "value": 184108}, {"id": "407124", "parent": "1103", "name": "叶苗苗", "value": 12355}, {"id": "407121", "parent": "1103", "name": "孙语姗", "value": 8655}, {"id": "407110", "parent": "1103", "name": "刘闲", "value": 38088}, {"id": "327598", "parent": "1102", "name": "张笑盈", "value": 75450}, {"id": "327595", "parent": "1102", "name": "郑一凡", "value": 140}, {"id": "327587", "parent": "1102", "name": "冯思佳", "value": 3360}, {"id": "327580", "parent": "1101", "name": "张梦慧", "value": 20210}, {"id": "327579", "parent": "1101", "name": "刘姝贤", "value": 54021}, {"id": "63571", "parent": "1101", "name": "田姝丽", "value": 50640}, {"id": "63559", "parent": "1101", "name": "胡晓慧", "value": 293080}, {"id": "6745", "parent": "1101", "name": "闫明筠", "value": 2490}]}